django_stripe/__init__.py
django_stripe/actions/__init__.py
django_stripe/actions/billings.py
django_stripe/actions/core.py
django_stripe/actions/events.py
django_stripe/actions/mixins.py
django_stripe/actions/payment_methods.py
django_stripe/actions/products.py
django_stripe/actions/webhooks.py
django_stripe/admin/__init__.py
django_stripe/admin/abstracts.py
django_stripe/admin/billings/__init__.py
django_stripe/admin/billings/subscriptions.py
django_stripe/admin/core/__init__.py
django_stripe/admin/core/customers.py
django_stripe/admin/core/events.py
django_stripe/admin/products/__init__.py
django_stripe/admin/products/coupons.py
django_stripe/admin/products/prices.py
django_stripe/admin/products/products.py
django_stripe/apps.py
django_stripe/base/__init__.py
django_stripe/base/webhooks.py
django_stripe/exceptions.py
django_stripe/management/__init__.py
django_stripe/management/commands/__init__.py
django_stripe/management/commands/sync_stripe_coupons.py
django_stripe/management/commands/sync_stripe_customers.py
django_stripe/management/commands/sync_stripe_prices.py
django_stripe/management/commands/sync_stripe_products.py
django_stripe/migrations/__init__.py
django_stripe/models/__init__.py
django_stripe/models/abstracts/__init__.py
django_stripe/models/abstracts/billings/__init__.py
django_stripe/models/abstracts/billings/subscriptions.py
django_stripe/models/abstracts/core/__init__.py
django_stripe/models/abstracts/core/customers.py
django_stripe/models/abstracts/core/events.py
django_stripe/models/abstracts/mixins.py
django_stripe/models/abstracts/payment_methods/__init__.py
django_stripe/models/abstracts/payment_methods/cards.py
django_stripe/models/abstracts/products/__init__.py
django_stripe/models/abstracts/products/coupons.py
django_stripe/models/abstracts/products/prices.py
django_stripe/models/abstracts/products/products.py
django_stripe/models/billings/__init__.py
django_stripe/models/billings/subscriptions.py
django_stripe/models/core/__init__.py
django_stripe_plus-0.2.0.dist-info/LICENSE
django_stripe_plus-0.2.0.dist-info/METADATA
django_stripe_plus-0.2.0.dist-info/WHEEL
django_stripe_plus-0.2.0.dist-info/RECORD
