Metadata-Version: 2.1
Name: django-stripe-plus
Version: 0.2.0
Summary: Django + Stripe made easy
Home-page: https://purnendukar.github.io/django-stripe
License: MIT
Keywords: django-stripe
Author: Purnendu Kar
Author-email: purnendu.kar8@gmail.com
Maintainer: Purnendu Kar
Maintainer-email: purnendu.kar8@gmail.com
Requires-Python: >=3.9,<4.0
Classifier: Development Status :: 5 - Production/Stable
Classifier: Framework :: Django
Classifier: Framework :: Django :: 4.0
Classifier: Framework :: Django :: 4.1
Classifier: Framework :: Django :: 4.2
Classifier: Framework :: Django :: 5.0
Classifier: Framework :: Django :: 5.1
Classifier: Intended Audience :: Developers
Classifier: License :: OSI Approved :: MIT License
Classifier: Natural Language :: English
Classifier: Operating System :: OS Independent
Classifier: Programming Language :: Python :: 3
Classifier: Programming Language :: Python :: 3.9
Classifier: Programming Language :: Python :: 3.10
Classifier: Programming Language :: Python :: 3.11
Classifier: Programming Language :: Python :: 3.12
Requires-Dist: django (>=4.0,<5.0)
Requires-Dist: stripe (>=10.8,<11.0)
Project-URL: Documentation, https://purnendukar.github.io/django-stripe
Project-URL: Repository, https://github.com/purnendukar/django-stripe
